byma/__init__.py
byma/_version.py
byma/interface/BaseInterface.py
byma/interface/NonlinearHeat.py
byma/interface/Time.py
byma/interface/__init__.py
byma/iteral/GradientDescent.py
byma/iteral/Iteral.py
byma/iteral/NesterovMethod.py
byma/iteral/Newton.py
byma/iteral/OrthogonalSubspace.py
byma/iteral/__init__.py
byma/nuby/Bifurcation.py
byma/nuby/Continuation.py
byma/nuby/__init__.py
byma/nuby/_nuby.py
byma/numy/Numy.py
byma/numy/__init__.py
byma/numy/_numy.py
byma/numy/integration.py
byma/numy/regression.py
byma/pyplot/__init__.py
byma/pyplot/plots.py
tests/__init__.py
byma-0.1.11.dist-info/LICENSE.md
byma-0.1.11.dist-info/METADATA
byma-0.1.11.dist-info/WHEEL
byma-0.1.11.dist-info/top_level.txt
byma-0.1.11.dist-info/RECORD
