Metadata-Version: 2.1
Name: byma
Version: 0.1.11
Summary: A Numerical Mathematics Packages with an easier and clean user interface.
Author: @b64-Lorenzo (Lorenzo Zambelli)
Author-email: Lorenzo Zambelli <bytemath@lorenzozambelli.it>
Project-URL: Homepage, https://gitlab.com/ByteMath/python/byma
Project-URL: documentation, https://bytemath.gitlab.io/python/ByMa/index.html
Project-URL: source, https://gitlab.com/ByteMath/python/ByMa
Project-URL: download, https://pypi.org/project/byma/#files
Project-URL: tracker, https://gitlab.com/ByteMath/python/ByMa/-/issues
Keywords: python,scientific,numerical,bifurcation
Classifier: Programming Language :: Python :: 3
Classifier: License :: OSI Approved :: BSD License
Classifier: Topic :: Scientific/Engineering
Classifier: Operating System :: OS Independent
Requires-Python: >=3.7
License-File: LICENSE.md
